echo/__init__.py
echo/__main__.py
echo/client.py
echo/client_console.py
echo/client_gui.py
echo/server.py
echo/db/__init__.py
echo/db/server.py
echo/db/server_repo.py
echo/helpers/__init__.py
echo/helpers/console.py
echo/helpers/jim.py
echo/log/__init__.py
echo/log/client.py
echo/log/server.py
echo/ui/__init__.py
echo/ui/client.py
echo/ui/client.ui
echo/ui/client2.py
echo_messenger-0.32.dist-info/DESCRIPTION.rst
echo_messenger-0.32.dist-info/METADATA
echo_messenger-0.32.dist-info/RECORD
echo_messenger-0.32.dist-info/WHEEL
echo_messenger-0.32.dist-info/metadata.json
echo_messenger-0.32.dist-info/top_level.txt
src/__main__.py
src/client.py
src/client_console.py
src/client_gui.py
src/server.py
