Metadata-Version: 2.0
Name: echo-messenger
Version: 0.32
Summary: JIM messenger
Home-page: https://github.com/smaskin/echo
Author: Sergey Maskin
Author-email: s.maskin@mail.ru
License: MIT
Keywords: python,messenger,jim
Platform: UNKNOWN
Requires-Python: >=3.5
Requires-Dist: PyQt5 (==5.9)
Requires-Dist: SQLAlchemy (==1.1.15)
